redsauce/__init__.py
redsauce/pickles.py
redsauce/utensils.py
redsauce/utility/__init__.py
redsauce/utility/logging.py
redsauce-0.0.1.11.dist-info/LICENSE
redsauce-0.0.1.11.dist-info/METADATA
redsauce-0.0.1.11.dist-info/WHEEL
redsauce-0.0.1.11.dist-info/top_level.txt
redsauce-0.0.1.11.dist-info/RECORD
