Metadata-Version: 2.1
Name: redsauce
Version: 0.0.1.11
Author: Eric DiGioacchino
Author-email: eric.digioacchino01@gmail.com
License-File: LICENSE
Requires-Dist: redis[hiredis]
